{
  "data": [
    [
      {
        "id": "30323772",
        "recordType": "salesorder",
        "ISA06": "BEACHHOUSEMOON",
        "ISA08": "TST1MECCABRANDS",
        "e1004": "SO12465617",
        "e2380": "20231110",
        "e1154": "VPO-0241305",
        "e5004": "14288.40",
        "e3039": "MOONBE",
        "e3036": "Moon Oral Beauty",
        "e7140a": "00850000948365",
        "e7140b": "I-064762",
        "e7140c": "MOON319152",
        "e6060": "1944",
        "e1082": "1",
        "e1229": "5",
        "e7008": "Moon KENDALL JENNER Whitening Pen Vanilla Mint Global",
        "e5118": "7.35",
        "dataURI": "https://4675206-sb1.app.netsuite.com/app/accounting/transactions/salesord.nl?id=30323772&compid=4675206_SB1"
      },
      {
        "id": "30323772",
        "recordType": "salesorder",
        "ISA06": "BEACHHOUSEMOON",
        "ISA08": "TST1MECCABRANDS",
        "e1004": "SO12465617",
        "e2380": "20231110",
        "e1154": "VPO-0241305",
        "e5004": "3784.20",
        "e3039": "MOONBE",
        "e3036": "Moon Oral Beauty",
        "e7140a": "00850000948242",
        "e7140b": "I-064764",
        "e7140c": "MOON319139",
        "e6060": "636",
        "e1082": "2",
        "e1229": "5",
        "e7008": "Moon Dust Advanced Whitening Paste Booster",
        "e5118": "5.95",
        "dataURI": "/app/accounting/transactions/salesord.nl?id=30323772&compid=4675206_SB1"
      },
      {
        "id": "30323772",
        "recordType": "salesorder",
        "ISA06": "BEACHHOUSEMOON",
        "ISA08": "TST1MECCABRANDS",
        "e1004": "SO12465617",
        "e2380": "20231110",
        "e1154": "VPO-0241305",
        "e5004": "8085.00",
        "e3039": "MOONBE",
        "e3036": "Moon Oral Beauty",
        "e7140a": "00850000948952",
        "e7140b": "I-064765",
        "e7140c": "MOON432254",
        "e6060": "330",
        "e1082": "3",
        "e1229": "5",
        "e7008": "Moon The Electric Toothbrush Global",
        "e5118": "24.50",
        "dataURI": "/app/accounting/transactions/salesord.nl?id=30323772&compid=4675206_SB1"
      },
      {
        "id": "30323772",
        "recordType": "salesorder",
        "ISA06": "BEACHHOUSEMOON",
        "ISA08": "TST1MECCABRANDS",
        "e1004": "SO12465617",
        "e2380": "20231110",
        "e1154": "VPO-0241305",
        "e5004": "3742.20",
        "e3039": "MOONBE",
        "e3036": "Moon Oral Beauty",
        "e7140a": "00850000948006",
        "e7140b": "I-064766",
        "e7140c": "MOON119102",
        "e6060": "1188",
        "e1082": "4",
        "e1229": "5",
        "e7008": "Moon Soft Bristle Toothbrush 2pack",
        "e5118": "3.15",
        "dataURI": "/app/accounting/transactions/salesord.nl?id=30323772&compid=4675206_SB1"
      },
      {
        "id": "30323772",
        "recordType": "salesorder",
        "ISA06": "BEACHHOUSEMOON",
        "ISA08": "TST1MECCABRANDS",
        "e1004": "SO12465617",
        "e2380": "20231110",
        "e1154": "VPO-0241305",
        "e5004": "330.75",
        "e3039": "MOONBE",
        "e3036": "Moon Oral Beauty",
        "e7140a": "00850000948976",
        "e7140b": "I-064767",
        "e7140c": "MOON322265",
        "e6060": "63",
        "e1082": "5",
        "e1229": "5",
        "e7008": "Moon The Electric Toothbrush Replacement Heads (2 heads) w Pouch",
        "e5118": "5.25",
        "dataURI": "/app/accounting/transactions/salesord.nl?id=30323772&compid=4675206_SB1"
      },
      {
        "id": "30323772",
        "recordType": "salesorder",
        "ISA06": "BEACHHOUSEMOON",
        "ISA08": "TST1MECCABRANDS",
        "e1004": "SO12465617",
        "e2380": "20231110",
        "e1154": "VPO-0241305",
        "e5004": "4368.00",
        "e3039": "MOONBE",
        "e3036": "Moon Oral Beauty",
        "e7140a": "00850000948013",
        "e7140b": "I-064768",
        "e7140c": "MOON425247",
        "e6060": "1040",
        "e1082": "6",
        "e1229": "5",
        "e7008": "Moon Activated Charcoal Whitening Toothpaste Ffree UDI ASSEMBLY",
        "e5118": "4.20",
        "dataURI": "/app/accounting/transactions/salesord.nl?id=30323772&compid=4675206_SB1"
      },
      {
        "id": "30323772",
        "recordType": "salesorder",
        "ISA06": "BEACHHOUSEMOON",
        "ISA08": "TST1MECCABRANDS",
        "e1004": "SO12465617",
        "e2380": "20231110",
        "e1154": "VPO-0241305",
        "e5004": "6115.20",
        "e3039": "MOONBE",
        "e3036": "Moon Oral Beauty",
        "e7140a": "00850000948020",
        "e7140b": "I-064769",
        "e7140c": "MOON339261",
        "e6060": "1456",
        "e1082": "7",
        "e1229": "5",
        "e7008": "Moon-Stain Removal Whitening Toothpaste  FFree ASSEMBLY UDI",
        "e5118": "4.20",
        "dataURI": "/app/accounting/transactions/salesord.nl?id=30323772&compid=4675206_SB1"
      },
      {
        "id": "30323772",
        "recordType": "salesorder",
        "ISA06": "BEACHHOUSEMOON",
        "ISA08": "TST1MECCABRANDS",
        "e1004": "SO12465617",
        "e2380": "20231110",
        "e1154": "VPO-0241305",
        "e5004": "5376.00",
        "e3039": "MOONBE",
        "e3036": "Moon Oral Beauty",
        "e7140a": "00850000948839",
        "e7140b": "I-064770",
        "e7140c": "MOON122241",
        "e6060": "1024",
        "e1082": "8",
        "e1229": "5",
        "e7008": "Moon Platinum Fluoride Mint Toothpaste ASSEMBLY",
        "e5118": "5.25",
        "dataURI": "/app/accounting/transactions/salesord.nl?id=30323772&compid=4675206_SB1"
      }
    ]
  ],
  "errors": [],
  "_exportId": "65f85d52d69b359a5776e59b",
  "_connectionId": "63513d8e26e4db667eca7a36",
  "_flowId": "65f4953cdaa46ab5c0d9bfc6",
  "_integrationId": "64b57d01d3b06b1243405ab1",
  "pageIndex": 0,
  "settings": {
    "integration": {},
    "flowGrouping": {},
    "flow": {},
    "export": {},
    "connection": {},
    "iClient": {}
  },
  "testMode": true
}